getMultiPrimerSet/getMultiPrimerSet.py
getMultiPrimerSet-1.0.2.dist-info/METADATA
getMultiPrimerSet-1.0.2.dist-info/WHEEL
getMultiPrimerSet-1.0.2.dist-info/entry_points.txt
getMultiPrimerSet-1.0.2.dist-info/top_level.txt
getMultiPrimerSet-1.0.2.dist-info/RECORD
