Metadata-Version: 2.1
Name: getMultiPrimerSet
Version: 1.0.2
Summary: A package for generating multiplex PCR primer sets
Author: Jason D Limberis
Author-email: Jason.Limberis@ucsf.edu
License: UNKNOWN
Platform: UNKNOWN
Requires-Dist: biopython
Requires-Dist: pandas
Requires-Dist: numpy
Requires-Dist: primer3-py
